[
  {
    "_id": "54da5787242d70760e83c241",
    "index": 0,
    "guid": "073b8fe9-4dd8-4eaa-8291-0be4ffa5391a",
    "isActive": true,
    "balance": "$3,104.86",
    "picture": "http://placehold.it/32x32",
    "age": 27,
    "eyeColor": "brown",
    "name": "Mcgowan Black",
    "gender": "male",
    "company": "GEEKOLA",
    "email": "mcgowanblack@geekola.com",
    "phone": "+1 (903) 528-2576",
    "address": "362 Morton Street, Hebron, Connecticut, 2776",
    "about": "Eu occaecat et duis consequat est irure laborum proident cillum dolore laboris et. Magna consequat ea qui reprehenderit nisi sit consectetur. Nostrud nulla mollit cupidatat irure velit ipsum nisi laborum in tempor id est minim. Excepteur laboris velit eu incididunt. Aute incididunt magna enim culpa ipsum esse reprehenderit elit cupidatat eiusmod ullamco sint.\r\n",
    "registered": "2014-09-07T16:08:04 +05:00",
    "latitude": -65.045533,
    "longitude": 35.248256,
    "tags": [
      "culpa",
      "officia",
      "laboris",
      "do",
      "Lorem",
      "est",
      "anim"
    ],
    "friends": [
      {
        "id": 0,
        "name": "Kate Abbott"
      },
      {
        "id": 1,
        "name": "Tisha Albert"
      },
      {
        "id": 2,
        "name": "Clarke Randolph"
      }
    ],
    "greeting": "Hello, Mcgowan Black! You have 4 unread messages.",
    "favoriteFruit": "apple"
  },
  {
    "_id": "54da57875ba9daea7b7a02ab",
    "index": 1,
    "guid": "ca261fc1-6b0d-4ca5-8928-b3ffe44015ab",
    "isActive": true,
    "balance": "$3,495.59",
    "picture": "http://placehold.it/32x32",
    "age": 29,
    "eyeColor": "brown",
    "name": "Jaime Lowery",
    "gender": "female",
    "company": "OBLIQ",
    "email": "jaimelowery@obliq.com",
    "phone": "+1 (842) 497-3028",
    "address": "901 Walker Court, Bawcomville, Nebraska, 1190",
    "about": "Ex Lorem et elit exercitation aliqua sit nostrud. Anim ex occaecat dolore consequat proident fugiat mollit enim exercitation ex veniam nulla. Pariatur culpa aliqua aliqua cupidatat officia incididunt aliqua elit ipsum fugiat irure ad dolore. Anim adipisicing officia ex quis dolore nisi in id. Qui aute et esse cillum. In esse eu non enim pariatur magna culpa laborum quis excepteur est. Aute laboris deserunt proident sunt occaecat est anim est ut nostrud.\r\n",
    "registered": "2014-04-21T20:35:29 +05:00",
    "latitude": 35.725086,
    "longitude": 3.080134,
    "tags": [
      "dolor",
      "labore",
      "cillum",
      "aliqua",
      "occaecat",
      "aute",
      "ipsum"
    ],
    "friends": [
      {
        "id": 0,
        "name": "Hatfield Raymond"
      },
      {
        "id": 1,
        "name": "Natasha Mercado"
      },
      {
        "id": 2,
        "name": "Phelps Nelson"
      }
    ],
    "greeting": "Hello, Jaime Lowery! You have 8 unread messages.",
    "favoriteFruit": "strawberry"
  },
  {
    "_id": "54da57871a82dc8dbf115369",
    "index": 2,
    "guid": "34718f09-4a81-4709-9125-361bbade7d17",
    "isActive": true,
    "balance": "$1,674.39",
    "picture": "http://placehold.it/32x32",
    "age": 25,
    "eyeColor": "brown",
    "name": "Diann Greene",
    "gender": "female",
    "company": "QUADEEBO",
    "email": "dianngreene@quadeebo.com",
    "phone": "+1 (942) 418-2981",
    "address": "350 Oriental Boulevard, Loyalhanna, Virginia, 6556",
    "about": "Commodo voluptate velit do cupidatat fugiat minim velit enim duis reprehenderit dolor. Elit culpa nisi reprehenderit proident non ut mollit ex. Laboris cillum duis in mollit cupidatat excepteur labore amet eu adipisicing. Voluptate officia minim in reprehenderit cupidatat aliquip labore. Voluptate duis excepteur fugiat veniam quis mollit aute in culpa ut occaecat. Minim Lorem minim voluptate Lorem Lorem aliqua.\r\n",
    "registered": "2014-07-25T13:42:31 +05:00",
    "latitude": -11.033916,
    "longitude": 80.449024,
    "tags": [
      "cupidatat",
      "ea",
      "veniam",
      "cillum",
      "ut",
      "quis",
      "consequat"
    ],
    "friends": [
      {
        "id": 0,
        "name": "Summers Dale"
      },
      {
        "id": 1,
        "name": "Latisha Barnett"
      },
      {
        "id": 2,
        "name": "Cummings Beach"
      }
    ],
    "greeting": "Hello, Diann Greene! You have 5 unread messages.",
    "favoriteFruit": "strawberry"
  },
  {
    "_id": "54da5787b8146f56bd2f263d",
    "index": 3,
    "guid": "046d77bf-a0a8-40df-af57-7dd4d35e1162",
    "isActive": false,
    "balance": "$1,086.74",
    "picture": "http://placehold.it/32x32",
    "age": 22,
    "eyeColor": "green",
    "name": "Jodie Hewitt",
    "gender": "female",
    "company": "DOGTOWN",
    "email": "jodiehewitt@dogtown.com",
    "phone": "+1 (803) 577-3966",
    "address": "739 Empire Boulevard, Cawood, Delaware, 6517",
    "about": "Ex nulla amet dolor tempor exercitation excepteur officia. Amet velit est dolore dolore. Dolore nulla reprehenderit ipsum cillum dolore anim esse enim consequat ullamco id. Amet dolore fugiat in dolor officia ut officia et esse ex magna nulla. Eu occaecat consectetur quis tempor in ullamco sit cillum qui sit aute. Ullamco laborum dolore dolore et consectetur nisi aliquip dolore.\r\n",
    "registered": "2014-06-02T20:32:08 +05:00",
    "latitude": 51.719132,
    "longitude": 13.434798,
    "tags": [
      "sit",
      "sit",
      "sint",
      "velit",
      "eiusmod",
      "duis",
      "est"
    ],
    "friends": [
      {
        "id": 0,
        "name": "Curtis Coffey"
      },
      {
        "id": 1,
        "name": "Bowman Wells"
      },
      {
        "id": 2,
        "name": "Adkins Miles"
      }
    ],
    "greeting": "Hello, Jodie Hewitt! You have 3 unread messages.",
    "favoriteFruit": "banana"
  },
  {
    "_id": "54da5787ee4b2c42da8e2872",
    "index": 4,
    "guid": "1aa6f853-a3b3-4b6c-91cf-48d53fed6e27",
    "isActive": true,
    "balance": "$3,676.02",
    "picture": "http://placehold.it/32x32",
    "age": 39,
    "eyeColor": "blue",
    "name": "Hamilton Snyder",
    "gender": "male",
    "company": "TERRASYS",
    "email": "hamiltonsnyder@terrasys.com",
    "phone": "+1 (973) 600-3217",
    "address": "932 Covert Street, Tivoli, New Hampshire, 5275",
    "about": "Aliqua ad proident aute consectetur esse minim Lorem incididunt culpa ea minim excepteur. Labore excepteur adipisicing exercitation voluptate sit consectetur duis in. Officia nulla dolor consectetur aliqua. Proident ipsum cillum veniam minim ipsum ea excepteur dolore ea et magna reprehenderit do. Elit eiusmod eu incididunt cupidatat esse veniam irure est commodo et incididunt duis minim. Aliquip et pariatur velit veniam magna aute ullamco labore commodo pariatur occaecat nisi tempor dolore.\r\n",
    "registered": "2015-01-01T20:37:24 +06:00",
    "latitude": -3.509456,
    "longitude": 53.994392,
    "tags": [
      "dolor",
      "adipisicing",
      "nisi",
      "fugiat",
      "labore",
      "pariatur",
      "culpa"
    ],
    "friends": [
      {
        "id": 0,
        "name": "Hartman Patrick"
      },
      {
        "id": 1,
        "name": "Hill Woodward"
      },
      {
        "id": 2,
        "name": "Kinney Sutton"
      }
    ],
    "greeting": "Hello, Hamilton Snyder! You have 6 unread messages.",
    "favoriteFruit": "apple"
  },
  {
    "_id": "54da57873029c0339cf97eb8",
    "index": 5,
    "guid": "4104c91c-9723-4675-b760-712b8e26a141",
    "isActive": true,
    "balance": "$2,847.65",
    "picture": "http://placehold.it/32x32",
    "age": 29,
    "eyeColor": "blue",
    "name": "Celeste Perkins",
    "gender": "female",
    "company": "TELEQUIET",
    "email": "celesteperkins@telequiet.com",
    "phone": "+1 (855) 446-2386",
    "address": "128 Meserole Street, Barrelville, Oregon, 6258",
    "about": "Proident minim ad ea dolor in consequat. Est laboris laborum ullamco nostrud. Non deserunt nostrud do ipsum velit ullamco qui.\r\n",
    "registered": "2014-05-06T05:05:32 +05:00",
    "latitude": 89.315224,
    "longitude": -69.86909,
    "tags": [
      "proident",
      "ex",
      "est",
      "consequat",
      "est",
      "nulla",
      "culpa"
    ],
    "friends": [
      {
        "id": 0,
        "name": "Antoinette Dodson"
      },
      {
        "id": 1,
        "name": "Anna Pennington"
      },
      {
        "id": 2,
        "name": "Clayton Bentley"
      }
    ],
    "greeting": "Hello, Celeste Perkins! You have 3 unread messages.",
    "favoriteFruit": "strawberry"
  }
]